code_procrastinator/__init__.py
code_procrastinator/__main__.py
code_procrastinator/procrastinator.py
code_procrastinator-0.2.1.dist-info/licenses/LICENSE
code_procrastinator-0.2.1.dist-info/METADATA
code_procrastinator-0.2.1.dist-info/WHEEL
code_procrastinator-0.2.1.dist-info/entry_points.txt
code_procrastinator-0.2.1.dist-info/top_level.txt
code_procrastinator-0.2.1.dist-info/RECORD
