Metadata-Version: 2.4
Name: code_procrastinator
Version: 0.2.1
Summary: Python Package for functions that will procrastinate on their outputs
License:                     GNU GENERAL PUBLIC LICENSE
Keywords: python,package,build,tutorial
Classifier: Programming Language :: Python :: 3
Classifier: Intended Audience :: Education
Classifier: License :: OSI Approved :: GNU General Public License v3 (GPLv3)
Classifier: Operating System :: OS Independent
Requires-Python: >=3.7
License-File: LICENSE
Provides-Extra: dev
Requires-Dist: pytest; extra == "dev"
Dynamic: license-file
